{
  "project_name": "flask_graphql_mongo",
  "app_name": "graphql_api",
  "app_url": "http://localhost:9000",
  "python_version": ["3.7", "3.6", "3.7"],
  "log_to_file": ["yes", "no"],
  "log_file_max_bytes": 1000000,
  "log_file_backup_count": 10,
  "tox_python_env": "py{{ cookiecutter.python_version|replace('.','') }}",
  "sentry_sdk": ["yes", "no"],
  "mongo_url": "mongodb://localhost:27017",
  "mongo_db": "flask-graphql",
  "web_token_secret_key": "secret",
  "web_token_access_token_expires": "2400",
  "smtp": "smtp.mailtrap.io",
  "smtp_port": "587",
  "smtp_username": "4e0bf28f3d12fb",
  "smtp_password": "266a5d6e68e691",
  "version": "0.0.1",
  "author": "Sal",
  "open_source_license": ["MIT license", "BSD license", "ISC license", "Apache Software License 2.0", "GNU General Public License v3", "No License"],
  "docker_development" : ["no", "yes"],
  "start_server_after_generating_template": ["no", "yes"]
}
